{"_type":"export","__export_format":4,"__export_date":"2022-08-29T14:22:24.583Z","__export_source":"insomnia.desktop.app:v2022.5.0","resources":[{"_id":"req_49a01a4ca5fe4bd3b406e5cebc93ed7e","parentId":"fld_2f7bbae032d0478280284c5bdcf7e3c9","modified":1659448497931,"created":1659448416702,"url":"http://localhost:8989/api/ping","name":"Test Ping","description":"","method":"GET","body":{},"parameters":[],"headers":[],"authentication":{},"metaSortKey":-1659448416702,"isPrivate":false,"settingStoreCookies":true,"settingSendCookies":true,"settingDisableRenderRequestBody":false,"settingEncodeUrl":true,"settingRebuildPath":true,"settingFollowRedirects":"global","_type":"request"},{"_id":"fld_2f7bbae032d0478280284c5bdcf7e3c9","parentId":"wrk_b62daaa037c247f4adff53e54ef03eeb","modified":1659448413400,"created":1659448413400,"name":"KiwiCase","description":"","environment":{},"environmentPropertyOrder":null,"metaSortKey":-1659448413400,"_type":"request_group"},{"_id":"wrk_b62daaa037c247f4adff53e54ef03eeb","parentId":null,"modified":1657042052031,"created":1655817037770,"name":"New Document","description":"# AGENDAMENTO SOCIETY (INICIANDO PROJETO TEAM TASKS)\n\nProjeto consiste em:\n\nO proprietário do society irá conter um site/app onde o cliente poderá fazer o agendamento dos seus horários e também deixar agendando para futuras datas, poderá realizar o pagamento adiantando (pode ganhar % em desconto).\n\nNa parte do proprietário (Dashboard) iremos ter todo o controle de agendamento podendo excluir e incluir quando quiser, verificar os pagamentos e o cadastro dos clientes para efetuar ações de marketing.\n\nNo site/app irá conter um montador de time automático caso o cliente final.","scope":"design","_type":"workspace"},{"_id":"req_1f53a25257a54ee2a9a7e270ddaac3b9","parentId":"fld_2f7bbae032d0478280284c5bdcf7e3c9","modified":1659448908023,"created":1659448522964,"url":"http://localhost:8989/api/auth/login","name":"Login","description":"","method":"POST","body":{"mimeType":"multipart/form-data","params":[{"id":"pair_c808f95232ea4eafb02bc251a653b890","name":"document","value":"42127555805","description":""},{"id":"pair_9634d8b0f10e432fa92ea302805fe3c0","name":"password","value":"erick2020","description":""}]},"parameters":[],"headers":[{"name":"Content-Type","value":"multipart/form-data","id":"pair_636c095525634839b340e43f0ca8efc0"}],"authentication":{},"metaSortKey":-1657682849202,"isPrivate":false,"settingStoreCookies":true,"settingSendCookies":true,"settingDisableRenderRequestBody":false,"settingEncodeUrl":true,"settingRebuildPath":true,"settingFollowRedirects":"global","_type":"request"},{"_id":"req_70a8d42dc76343b0bb3fbf8a30c22f69","parentId":"fld_ef5fec58c4c049c5bf261a7e3f2343e5","modified":1657043340276,"created":1655917281642,"url":"{{base_url}}/api/company/field/delete/4","name":"DELETE FIELD","description":"Rota responsável pela exclusão do campo","method":"DELETE","body":{},"parameters":[],"headers":[],"authentication":{"type":"bearer","token":"{{ _.token }}"},"metaSortKey":-1655917281642,"isPrivate":false,"settingStoreCookies":true,"settingSendCookies":true,"settingDisableRenderRequestBody":false,"settingEncodeUrl":true,"settingRebuildPath":true,"settingFollowRedirects":"global","_type":"request"},{"_id":"fld_ef5fec58c4c049c5bf261a7e3f2343e5","parentId":"fld_d14623ba778d40369f4630f7cea1f009","modified":1655917281646,"created":1655917281646,"name":"DELETE","description":"","environment":{},"environmentPropertyOrder":null,"metaSortKey":-1655917281646,"_type":"request_group"},{"_id":"fld_d14623ba778d40369f4630f7cea1f009","parentId":"fld_34c5f4bc7c3c478f95865c55b569e76a","modified":1655917281666,"created":1655917281666,"name":"Request User Customers","description":"","environment":{},"environmentPropertyOrder":null,"metaSortKey":-1655917281666,"_type":"request_group"},{"_id":"fld_34c5f4bc7c3c478f95865c55b569e76a","parentId":"wrk_b62daaa037c247f4adff53e54ef03eeb","modified":1655917281708,"created":1655917281708,"name":"GoQuadra","description":"","environment":{},"environmentPropertyOrder":null,"metaSortKey":-1655917281708,"_type":"request_group"},{"_id":"req_9954d09ce92d4639b91965e98fc1c8ad","parentId":"fld_2cc880a818a04aa18c9f45e708dab9b0","modified":1660665188555,"created":1655917281648,"url":"{{base_url}}/api/company/field","name":"Create Field","description":"Rota responsável por criar um banco de dados e seus horários","method":"POST","body":{"mimeType":"multipart/form-data","params":[{"type":"text","name":"category_id","disabled":false,"value":"2","id":"pair_82974d1194884a988648d764dadffd7b"},{"type":"text","name":"title","disabled":false,"value":"Cadastro de quadra com horarios","id":"pair_2c1e7034160b442a996cf3238b4af158"},{"type":"text","name":"description","disabled":false,"value":"Descrição de Teste para quadra","id":"pair_07ef18c5e17243b9a1cd44dbb6883fab"},{"type":"text","name":"value","disabled":false,"value":"160","id":"pair_dccc3bbaea1446ac94f2be74353dd41e"},{"id":"pair_69af6531fdac4c17b9551e3321ed17aa","name":"weekday[]","value":"0","description":"","type":"text","multiline":false},{"id":"pair_6f108c06bc8949edb214837a3b83fe50","name":"start[]","value":"08:00:00","description":""},{"id":"pair_106633ac1bf343659d5a93c8d24aab01","name":"end[]","value":"16:00:00","description":""},{"id":"pair_581f465d343d44e0b2b0d7cb9acb7c85","name":"weekday[]","value":"1","description":""},{"id":"pair_7d681759e7b3477da285fed2a979889e","name":"start[]","value":"08:00:00","description":""},{"id":"pair_e1da9e5dd5624886b9477ea87d4170bd","name":"end[]","value":"18:00:00","description":""},{"id":"pair_ced08799dbe846a986b639c50cea76bf","name":"","value":"","description":""}]},"parameters":[],"headers":[],"authentication":{"type":"bearer","token":"{{ _.token }}"},"metaSortKey":-1655917281648,"isPrivate":false,"settingStoreCookies":true,"settingSendCookies":true,"settingDisableRenderRequestBody":false,"settingEncodeUrl":true,"settingRebuildPath":true,"settingFollowRedirects":"global","_type":"request"},{"_id":"fld_2cc880a818a04aa18c9f45e708dab9b0","parentId":"fld_d14623ba778d40369f4630f7cea1f009","modified":1655917281650,"created":1655917281650,"name":"POST","description":"","environment":{},"environmentPropertyOrder":null,"metaSortKey":-1655917281650,"_type":"request_group"},{"_id":"req_913b3f10675c479ab4564d35f8180825","parentId":"fld_2cc880a818a04aa18c9f45e708dab9b0","modified":1661782904355,"created":1660399108862,"url":"{{ _.base_url }}/api/company/send/notification","name":"Send Notification","description":"","method":"POST","body":{"mimeType":"multipart/form-data","params":[{"id":"pair_ebdb6f76c03d4cfd995f79d3ce4ba538","name":"message","value":"Olá, bem vindo ao GoQuadra, utilize o cupom DEV10 e ganhe desconto gratis","description":""}]},"parameters":[],"headers":[{"name":"Content-Type","value":"multipart/form-data","id":"pair_86cbf6c8a4c74d4fb4ed752fafdec89b"}],"authentication":{"type":"bearer","token":"{{ _.token }}"},"metaSortKey":-1660399108862,"isPrivate":false,"settingStoreCookies":true,"settingSendCookies":true,"settingDisableRenderRequestBody":false,"settingEncodeUrl":true,"settingRebuildPath":true,"settingFollowRedirects":"global","_type":"request"},{"_id":"req_6d80c51c895d47218e900f2d4decb8c0","parentId":"fld_01df2a1fed114b7aa1618a12926cd0e4","modified":1660174147213,"created":1657631584480,"url":"{{ _.base_url }}/api/company/field/edit/1","name":"Edit Field","description":"Rota responsável por criar um banco de dados e seus horários","method":"PUT","body":{"mimeType":"application/x-www-form-urlencoded","params":[{"type":"text","name":"category_id","disabled":false,"value":"2","id":"pair_82974d1194884a988648d764dadffd7b"},{"type":"text","name":"title","disabled":false,"value":"Campo de Teste Para alteração","id":"pair_2c1e7034160b442a996cf3238b4af158"},{"type":"text","name":"description","disabled":false,"value":"Descrição de Teste para quadra","id":"pair_07ef18c5e17243b9a1cd44dbb6883fab"},{"type":"text","name":"value","disabled":false,"value":"160","id":"pair_dccc3bbaea1446ac94f2be74353dd41e"},{"id":"pair_69af6531fdac4c17b9551e3321ed17aa","name":"weekday[]","value":"0","description":"","type":"text","multiline":false},{"id":"pair_6f108c06bc8949edb214837a3b83fe50","name":"start[]","value":"18:00:00","description":""},{"id":"pair_106633ac1bf343659d5a93c8d24aab01","name":"end[]","value":"23:00:00","description":""},{"id":"pair_581f465d343d44e0b2b0d7cb9acb7c85","name":"weekday[]","value":"1","description":""},{"id":"pair_7d681759e7b3477da285fed2a979889e","name":"start[]","value":"18:00:00","description":""},{"id":"pair_e1da9e5dd5624886b9477ea87d4170bd","name":"end[]","value":"23:00:00","description":""},{"id":"pair_ced08799dbe846a986b639c50cea76bf","name":"weekday[]","value":"2","description":""},{"id":"pair_f5545346a2404939b8013a7fe563a05a","name":"start[]","value":"18:00:00","description":""},{"id":"pair_983cdbc32fff4734917303aa26a8073f","name":"end[]","value":"23:00:00","description":""}]},"parameters":[],"headers":[{"name":"Content-Type","value":"application/x-www-form-urlencoded","id":"pair_473f101709d44c5e81b2ec442e00ef30"}],"authentication":{"type":"bearer","token":"{{ _.token }}"},"metaSortKey":-1655917281603,"isPrivate":false,"settingStoreCookies":true,"settingSendCookies":true,"settingDisableRenderRequestBody":false,"settingEncodeUrl":true,"settingRebuildPath":true,"settingFollowRedirects":"global","_type":"request"},{"_id":"fld_01df2a1fed114b7aa1618a12926cd0e4","parentId":"fld_d14623ba778d40369f4630f7cea1f009","modified":1655917281655,"created":1655917281655,"name":"PUT","description":"","environment":{},"environmentPropertyOrder":null,"metaSortKey":-1655917281655,"_type":"request_group"},{"_id":"req_31c1085ea6b44ff4839777c9a04cae58","parentId":"fld_c5469f10714c49c69c1a49f1513e3a58","modified":1657734250826,"created":1655917281658,"url":"{{base_url}}/api/company/field/edit/1","name":"Show Field One","description":"Rota responsável para a listagem de um único campo para efetuar a edição","method":"GET","body":{},"parameters":[],"headers":[],"authentication":{"type":"bearer","token":"{{ _.token }}"},"metaSortKey":-1655917281658,"isPrivate":false,"settingStoreCookies":true,"settingSendCookies":true,"settingDisableRenderRequestBody":false,"settingEncodeUrl":true,"settingRebuildPath":true,"settingFollowRedirects":"global","_type":"request"},{"_id":"fld_c5469f10714c49c69c1a49f1513e3a58","parentId":"fld_d14623ba778d40369f4630f7cea1f009","modified":1655917281664,"created":1655917281664,"name":"GET","description":"","environment":{},"environmentPropertyOrder":null,"metaSortKey":-1655917281664,"_type":"request_group"},{"_id":"req_80ed70f991b44f7ebe0a000ef60f758e","parentId":"fld_c5469f10714c49c69c1a49f1513e3a58","modified":1660172962251,"created":1655917281660,"url":"{{ _.base_url }}/api/company/fields","name":"List Fields","description":"Rota responsável pela listagem de todos os campos cadastrados","method":"GET","body":{"params":[{"type":"text","name":"category_id","disabled":true,"value":"2","id":"pair_4ada423ed4224173a9f34dd8f102821c"},{"type":"text","name":"title","disabled":true,"value":"Quadra 02 Coberta","id":"pair_2f225a08f16b44f79b2f0056a137c632"},{"type":"text","name":"description","disabled":true,"value":"Curabitur arcu erat, accumsan id imperdiet et, porttitor at sem. Donec rutrum congue leo eget malesuada. Nulla porttitor accumsan tincidunt. Curabitur aliquet quam id dui posuere blandit. Pellentesque in ipsum id orci porta dapibus.","id":"pair_c235bcdea6eb4147b16b550a7009ee91"},{"type":"text","name":"value","disabled":true,"value":"160","id":"pair_db1d3f8f43294edc9cb627271f57cd37"}],"mimeType":"multipart/form-data"},"parameters":[],"headers":[],"authentication":{"type":"bearer","token":"{{ _.token }}"},"metaSortKey":-1655917281660,"isPrivate":false,"settingStoreCookies":true,"settingSendCookies":true,"settingDisableRenderRequestBody":false,"settingEncodeUrl":true,"settingRebuildPath":true,"settingFollowRedirects":"global","_type":"request"},{"_id":"req_ee9e5c5669124ed8adce8d5f95eae9f4","parentId":"fld_c5469f10714c49c69c1a49f1513e3a58","modified":1657654014859,"created":1655917281662,"url":"{{ _.base_production }}/api/company/dash","name":"List Dashboard","description":"Rota para o empresário, onde o mesmo poderá visualizar todas as informações referente a sua empresa","method":"GET","body":{},"parameters":[],"headers":[],"authentication":{"type":"bearer","token":"{{ _.token }}"},"metaSortKey":-1655917281662,"isPrivate":false,"settingStoreCookies":true,"settingSendCookies":true,"settingDisableRenderRequestBody":false,"settingEncodeUrl":true,"settingRebuildPath":true,"settingFollowRedirects":"global","_type":"request"},{"_id":"req_b058c5bfe1f24af0a74d4004a0ea9c57","parentId":"fld_c5469f10714c49c69c1a49f1513e3a58","modified":1657654018255,"created":1656600949706,"url":"{{ _.base_production }}/api/company/categories","name":"List Categories","description":"Rota responsável para listagem das categorias quando o usuário for registrar um campo","method":"GET","body":{"mimeType":"multipart/form-data","params":[]},"parameters":[],"headers":[],"authentication":{"type":"bearer","token":"{{ _.token }}"},"metaSortKey":-1655917281659,"isPrivate":false,"settingStoreCookies":true,"settingSendCookies":true,"settingDisableRenderRequestBody":false,"settingEncodeUrl":true,"settingRebuildPath":true,"settingFollowRedirects":"global","_type":"request"},{"_id":"req_c47b1540e18e4857a0741d2175608899","parentId":"fld_b8bc1cbfa36e49edb479ce60974d4222","modified":1659723757371,"created":1655917281667,"url":"{{ _.base_production }}/api/app/user","name":"Update User","description":"Rota responsável para atualizar as informações do usuário sem a imagem","method":"PUT","body":{"mimeType":"application/x-www-form-urlencoded","params":[{"type":"text","name":"name","disabled":false,"value":"Erick Cordeiro","id":"pair_5d35edce57fa45cdbfbd58f53650e453"},{"type":"text","name":"email","disabled":false,"value":"erickcordeiroa@gmail.com","id":"pair_78a0abdc162e4552b1f5e5d00e86155d"},{"id":"pair_cfec31cba225406daf4e76d1bc3cd94b","name":"city","value":"Cajati","description":""},{"id":"pair_435c93c1d47d47e4b0a1b99dd72c7b67","name":"state","value":"São Paulo","description":""}]},"parameters":[],"headers":[{"name":"Content-Type","value":"application/x-www-form-urlencoded","id":"pair_3c21aaa91f2e4632a9f045ae6758888b"}],"authentication":{"type":"bearer","token":"{{ _.token }}"},"metaSortKey":-1655917281667,"isPrivate":false,"settingStoreCookies":true,"settingSendCookies":true,"settingDisableRenderRequestBody":false,"settingEncodeUrl":true,"settingRebuildPath":true,"settingFollowRedirects":"global","_type":"request"},{"_id":"fld_b8bc1cbfa36e49edb479ce60974d4222","parentId":"fld_68f11b268ad54ca7928b038375467b4a","modified":1655917281670,"created":1655917281670,"name":"PUT","description":"","environment":{},"environmentPropertyOrder":null,"metaSortKey":-1655917281670,"_type":"request_group"},{"_id":"fld_68f11b268ad54ca7928b038375467b4a","parentId":"fld_34c5f4bc7c3c478f95865c55b569e76a","modified":1655917281705,"created":1655917281705,"name":"Requests User App","description":"","environment":{},"environmentPropertyOrder":null,"metaSortKey":-1655917281705,"_type":"request_group"},{"_id":"req_40315a80b3a14db691bceb4f4c04734a","parentId":"fld_14a6b740bed94cc8b1a1046e027f261a","modified":1660399104007,"created":1655909670911,"url":"{{ _.base_url }}/api/app/tenant/1/appointment","name":"Appointment","description":"Rota responsável para criar o agendamento da quadra","method":"POST","body":{"mimeType":"multipart/form-data","params":[{"id":"pair_c738076751f14824bcb102b6e81824fb","name":"field","value":"1","description":""},{"id":"pair_680a4a854e7945cca6461383be68d97e","name":"payment","value":"2","description":""},{"id":"pair_51d846cca94441ac9326ca43d63cf8d0","name":"year","value":"2022","description":""},{"id":"pair_d31b64c044a240de8f8c6fdd9bc7c2dd","name":"month","value":"06","description":""},{"id":"pair_74600c7f9cbc495795348e084f59a462","name":"day","value":"27","description":""},{"id":"pair_78d98e0ba1244e9ba86da32b383f99f9","name":"hours","value":"11","description":""}]},"parameters":[],"headers":[{"name":"Content-Type","value":"multipart/form-data","id":"pair_ea86bc4b69aa484680d8d6c20a4bd0e8"}],"authentication":{"type":"bearer","token":"{{ _.token }}"},"metaSortKey":-1655917281623,"isPrivate":false,"settingStoreCookies":true,"settingSendCookies":true,"settingDisableRenderRequestBody":false,"settingEncodeUrl":true,"settingRebuildPath":true,"settingFollowRedirects":"global","_type":"request"},{"_id":"fld_14a6b740bed94cc8b1a1046e027f261a","parentId":"fld_68f11b268ad54ca7928b038375467b4a","modified":1655917281690,"created":1655917281690,"name":"POST","description":"","environment":{},"environmentPropertyOrder":null,"metaSortKey":-1655917281690,"_type":"request_group"},{"_id":"req_6f267b445eb84d3a8a2243a1551217dc","parentId":"fld_14a6b740bed94cc8b1a1046e027f261a","modified":1659555712652,"created":1655917281673,"url":"{{ _.base_production }}/api/app/user/avatar","name":"Avatar User","description":"Rota responsável para alterar a imagem do usuário, apenas utilizar no aplicativo","method":"POST","body":{"mimeType":"multipart/form-data","params":[{"type":"file","name":"avatar","disabled":false,"fileName":"D:\\Pictures\\1393881.jpg","id":"pair_a477a326f0784734a6b37ae3250d9006"}]},"parameters":[],"headers":[],"authentication":{"type":"bearer","token":"{{ _.token }}"},"metaSortKey":-1655917281673,"isPrivate":false,"settingStoreCookies":true,"settingSendCookies":true,"settingDisableRenderRequestBody":false,"settingEncodeUrl":true,"settingRebuildPath":true,"settingFollowRedirects":"global","_type":"request"},{"_id":"req_9f92d2d697ce429795948086789865db","parentId":"fld_14a6b740bed94cc8b1a1046e027f261a","modified":1657042792802,"created":1655917281677,"url":"{{ _.base_url }}/api/auth/logout","name":"Logout","description":"Rota responsável para efetuar o logout do aplicativo","method":"POST","body":{"mimeType":"multipart/form-data","params":[]},"parameters":[],"headers":[],"authentication":{"type":"bearer","token":"{{ _.token }}"},"metaSortKey":-1655917281677,"isPrivate":false,"settingStoreCookies":true,"settingSendCookies":true,"settingDisableRenderRequestBody":false,"settingEncodeUrl":true,"settingRebuildPath":true,"settingFollowRedirects":"global","_type":"request"},{"_id":"req_c3091c84a8594229ac0b6c1ceadfb3c0","parentId":"fld_14a6b740bed94cc8b1a1046e027f261a","modified":1657642780596,"created":1655917281680,"url":"{{ _.base_url }}/api/company/tenant","name":"Create Tenant","description":"Rota responsável para a inserção das informações da empresa no sistema, é importante resaltar que essa rota é para os usuário (empresários). Toda vez que um novo empresário realizar o cadastro vai estar precisando preencher essas informações para exibir na listagem para os clientes (usuários do app)","method":"POST","body":{"mimeType":"multipart/form-data","params":[{"type":"text","name":"company","disabled":false,"value":"WinnTenis Cadastro de Teste","id":"pair_d9428caeefab47e8b2706d1f55b2e05e"},{"type":"text","name":"fantasy","disabled":false,"value":"EWD Marketing Digital","id":"pair_641d9494f8fe4ada8a8419c8485ee449"},{"type":"text","name":"document","disabled":false,"value":"421275558055","id":"pair_ec1db248ee8d463091bcda2f3c180c2c"},{"type":"text","name":"address","disabled":false,"value":"Av. Clara Gianotti de Souza, 612","id":"pair_b50eb912ea94407ab6954eef81bcb66f"},{"type":"text","name":"city","disabled":false,"value":"Registro","id":"pair_2a137f7688e14927ad90a9bf57bc0167"},{"type":"text","name":"state","disabled":false,"value":"São Paulo","id":"pair_01ccff72301a4fd8a5c4cea09c275eea"},{"id":"pair_ba4a4a6a107844c594abebd24e17413a","name":"photo","value":"","description":"","type":"file","fileName":"D:\\Pictures\\1393881.jpg"},{"id":"pair_86cedf4a2e62496fbb092fc58038993a","name":"cover[]","value":"","description":"","type":"file","fileName":"D:\\Pictures\\agencia-wallpaper.jpg"},{"id":"pair_cacd84253cbe44ab9539f87648199216","name":"cover[]","value":"","description":"","type":"file","fileName":"D:\\Pictures\\agv-border-80.jpg"}]},"parameters":[],"headers":[],"authentication":{"type":"bearer","token":"{{ _.token }}"},"metaSortKey":-1655917281680,"isPrivate":false,"settingStoreCookies":true,"settingSendCookies":true,"settingDisableRenderRequestBody":false,"settingEncodeUrl":true,"settingRebuildPath":true,"settingFollowRedirects":"global","_type":"request"},{"_id":"req_d8d151e71ae94e328b343da2036d7e18","parentId":"fld_14a6b740bed94cc8b1a1046e027f261a","modified":1657042514616,"created":1655917281682,"url":"{{ _.base_production }}/api/auth/refresh","name":"Refresh","description":"Rota responsável para atualizar o token registrado quando o cliente do app ou do web fizer o login","method":"POST","body":{"mimeType":"multipart/form-data","params":[]},"parameters":[],"headers":[],"authentication":{"type":"bearer","token":"{{ _.token }}"},"metaSortKey":-1655917281682,"isPrivate":false,"settingStoreCookies":true,"settingSendCookies":true,"settingDisableRenderRequestBody":false,"settingEncodeUrl":true,"settingRebuildPath":true,"settingFollowRedirects":"global","_type":"request"},{"_id":"req_8a3f33e01b7c4b8db1eb627d1e53fec7","parentId":"fld_14a6b740bed94cc8b1a1046e027f261a","modified":1660598098183,"created":1655917281683,"url":"{{ _.base_production }}/api/auth/login","name":"Login","description":"Rota responsável para efetuar o login no sistema tanto no app como no sistema web","method":"POST","body":{"mimeType":"multipart/form-data","params":[{"type":"text","name":"email","disabled":false,"value":"erickcordeiroa@gmail.com","id":"pair_090cb0a25d2a450cb330f23930fd1a0a"},{"type":"text","name":"password","disabled":false,"value":"erick2020","id":"pair_2131d96c05764c34ad032c520839eed4"}]},"parameters":[],"headers":[],"authentication":{},"metaSortKey":-1655917281683,"isPrivate":false,"settingStoreCookies":true,"settingSendCookies":true,"settingDisableRenderRequestBody":false,"settingEncodeUrl":true,"settingRebuildPath":true,"settingFollowRedirects":"global","_type":"request"},{"_id":"req_bc892b1f2342410d8644450978b16500","parentId":"fld_14a6b740bed94cc8b1a1046e027f261a","modified":1659448414272,"created":1655917281686,"url":"{{ _.base_url }}/api/user","name":"Create User","description":"Rota responsável para criação de um novo usuário pelo app ou para o empresário","method":"POST","body":{"mimeType":"multipart/form-data","params":[{"type":"text","name":"name","disabled":false,"value":"Erick Cordeiro","id":"pair_de970621f60d48609d59724cf39758d5"},{"type":"text","name":"email","disabled":false,"value":"erickcordeiro3@gmail.com","id":"pair_bf34940e49ac486ba2ee967e60555ad9"},{"type":"text","name":"password","disabled":false,"value":"erick2020","id":"pair_b88773e3aa4b49cf942fe1853e282524"},{"id":"pair_2e887c6e539144168a00417c88125fde","name":"city","value":"Registro","description":""},{"id":"pair_3d6d3a378da042c5a3ddc05388f0308e","name":"state","value":"São Paulo","description":""},{"id":"pair_e4edfdeb1657430b8eaf54471baedce1","name":"device_token","value":"samsung","description":""}]},"parameters":[],"headers":[],"authentication":{"type":"bearer","token":"{{ _.token }}"},"metaSortKey":-1655917281686,"isPrivate":false,"settingStoreCookies":true,"settingSendCookies":true,"settingDisableRenderRequestBody":false,"settingEncodeUrl":true,"settingRebuildPath":true,"settingFollowRedirects":"global","_type":"request"},{"_id":"req_75bb69ac01f4417b84157ee96032c866","parentId":"fld_14a6b740bed94cc8b1a1046e027f261a","modified":1660610265244,"created":1655917281688,"url":"{{ _.base_production }}/api/app/tenant/search","name":"Search Company","description":"Rota para pesquisa de empresa por nome informando o parametro \"q\" e a cidade \"city\"","method":"POST","body":{"mimeType":"multipart/form-data","params":[{"type":"text","name":"q","disabled":false,"value":"EWD","id":"pair_06dc8e4ad5d445b993133ddfe8dcf0d8"},{"type":"text","name":"city","disabled":true,"value":"Registro","id":"pair_a50cd2e8e9964729a96190843c1db5f6"},{"id":"pair_65489b76a155446ba2d8a2b835e7f324","name":"category","value":"2","description":"","disabled":true}]},"parameters":[],"headers":[],"authentication":{"type":"bearer","token":"{{ _.token }}"},"metaSortKey":-1655917281688,"isPrivate":false,"settingStoreCookies":true,"settingSendCookies":true,"settingDisableRenderRequestBody":false,"settingEncodeUrl":true,"settingRebuildPath":true,"settingFollowRedirects":"global","_type":"request"},{"_id":"req_405f035b9bfe4ba78740425435848e67","parentId":"fld_14a6b740bed94cc8b1a1046e027f261a","modified":1657042843021,"created":1655924304883,"url":"{{base_url}}/api/app/user/favorite","name":"Favorite","description":"Rota responsável para favoritar ou desfavoritar a empresa para o usuário logado","method":"POST","body":{"mimeType":"multipart/form-data","params":[{"id":"pair_edec23c061ec4279929d61c63c968bca","name":"tenant","value":"1","description":""}]},"parameters":[],"headers":[],"authentication":{"type":"bearer","token":"{{ _.token }}"},"metaSortKey":-1655917281670,"isPrivate":false,"settingStoreCookies":true,"settingSendCookies":true,"settingDisableRenderRequestBody":false,"settingEncodeUrl":true,"settingRebuildPath":true,"settingFollowRedirects":"global","_type":"request"},{"_id":"req_e6cb744c9d5741a0bd98d77f5564cf77","parentId":"fld_14a6b740bed94cc8b1a1046e027f261a","modified":1657042450253,"created":1656419672851,"url":"{{ _.base_url }}/api/reset-password","name":"Reset Password","description":"Rota responsável para recuperação da senha, obrigatório informar o token que for enviado no e-mail como parametro, pois faz a verificação com o que esta vinculado no banco de dados","method":"POST","body":{"mimeType":"multipart/form-data","params":[{"id":"pair_69522dd14b6f4e0086d27ada1ce62d8e","name":"email","value":"erickcordeiroa@gmail.com","description":""},{"id":"pair_dc04a9463f004618b7abc927ce93630d","name":"password","value":"erick2020","description":""},{"id":"pair_af165bbc889b40c3af2106ccfff27242","name":"token","value":"$2y$10$CGhOhTDWR/QLGbKAHRf.teMex7y3HiNPCpe498qIbkeiwfwjU.sDi","description":""}]},"parameters":[],"headers":[],"authentication":{},"metaSortKey":-1655917281682.5,"isPrivate":false,"settingStoreCookies":true,"settingSendCookies":true,"settingDisableRenderRequestBody":false,"settingEncodeUrl":true,"settingRebuildPath":true,"settingFollowRedirects":"global","_type":"request"},{"_id":"req_d4376d9794ae4055b467245f42bd8d0c","parentId":"fld_14a6b740bed94cc8b1a1046e027f261a","modified":1657042489643,"created":1656596859356,"url":"{{ _.base_url }}/api/forgot-password","name":"Forgot","description":"Rota responsável por enviar o e-mail de recuperação de senha verificando se o e-mail esta cadastrado no banco de dados ou não","method":"POST","body":{"mimeType":"multipart/form-data","params":[{"type":"text","name":"email","disabled":false,"value":"erickcordeiroa@gmail.com","id":"pair_090cb0a25d2a450cb330f23930fd1a0a"}]},"parameters":[],"headers":[],"authentication":{},"metaSortKey":-1655917281682.25,"isPrivate":false,"settingStoreCookies":true,"settingSendCookies":true,"settingDisableRenderRequestBody":false,"settingEncodeUrl":true,"settingRebuildPath":true,"settingFollowRedirects":"global","_type":"request"},{"_id":"req_876def5ad678414e9133d8900fe1c45a","parentId":"fld_af1cfccd393940bab36bf00dc91b4a84","modified":1657046868521,"created":1655904074271,"url":"{{ _.base_url }}/api/company/dash","name":"Dash Tenant","description":"","method":"GET","body":{},"parameters":[],"headers":[],"authentication":{"type":"bearer","token":"{{ _.token }}"},"metaSortKey":-1655917281700.5,"isPrivate":false,"settingStoreCookies":true,"settingSendCookies":true,"settingDisableRenderRequestBody":false,"settingEncodeUrl":true,"settingRebuildPath":true,"settingFollowRedirects":"global","_type":"request"},{"_id":"fld_af1cfccd393940bab36bf00dc91b4a84","parentId":"fld_68f11b268ad54ca7928b038375467b4a","modified":1655917281703,"created":1655917281703,"name":"GET","description":"","environment":{},"environmentPropertyOrder":null,"metaSortKey":-1655917281703,"_type":"request_group"},{"_id":"req_b1d6c941ba5748b2967e33d9d00ee983","parentId":"fld_af1cfccd393940bab36bf00dc91b4a84","modified":1657042334888,"created":1655917281692,"url":"{{ _.base_production }}/api/app/user/appointments","name":"List User Appointments","description":"Listagem de todos os agendamentos realizado pelo usuário logado","method":"GET","body":{},"parameters":[],"headers":[],"authentication":{"type":"bearer","token":"{{ _.token }}"},"metaSortKey":-1655917281692,"isPrivate":false,"settingStoreCookies":true,"settingSendCookies":true,"settingDisableRenderRequestBody":false,"settingEncodeUrl":true,"settingRebuildPath":true,"settingFollowRedirects":"global","_type":"request"},{"_id":"req_88f67e5178234b2fa193e73f8fea8da5","parentId":"fld_af1cfccd393940bab36bf00dc91b4a84","modified":1657042259201,"created":1655917281693,"url":"https://api.goquadra.com.br/api/ping","name":"Test Pong","description":"Teste de verificação se a api esta online","method":"GET","body":{},"parameters":[],"headers":[],"authentication":{},"metaSortKey":-1655917281693,"isPrivate":false,"settingStoreCookies":true,"settingSendCookies":true,"settingDisableRenderRequestBody":false,"settingEncodeUrl":true,"settingRebuildPath":true,"settingFollowRedirects":"global","_type":"request"},{"_id":"req_578210fa7b364971a478a4d943661324","parentId":"fld_af1cfccd393940bab36bf00dc91b4a84","modified":1659015237161,"created":1655917281695,"url":"{{ _.base_url }}/api/app/user/favorites","name":"List Favorites","description":"Listagem de todas as empresas que o usuário logado deixou registrado como favorito","method":"GET","body":{},"parameters":[],"headers":[],"authentication":{"type":"bearer","token":"{{ _.token }}"},"metaSortKey":-1655917281695,"isPrivate":false,"settingStoreCookies":true,"settingSendCookies":true,"settingDisableRenderRequestBody":false,"settingEncodeUrl":true,"settingRebuildPath":true,"settingFollowRedirects":"global","_type":"request"},{"_id":"req_78c5f5f74ec94b4781766c060747e84d","parentId":"fld_af1cfccd393940bab36bf00dc91b4a84","modified":1660173010529,"created":1655917281697,"url":"{{ _.base_production }}/api/app/list/tenant/1","name":"List Company One","description":"Listagem de uma única empresa, informando todas as informações necessárias para as quadras, testemunhas, horários disponíveis, valores e fotos","method":"GET","body":{},"parameters":[],"headers":[],"authentication":{"type":"bearer","token":"{{ _.token }}"},"metaSortKey":-1655917281697,"isPrivate":false,"settingStoreCookies":true,"settingSendCookies":true,"settingDisableRenderRequestBody":false,"settingEncodeUrl":true,"settingRebuildPath":true,"settingFollowRedirects":"global","_type":"request"},{"_id":"req_b3d8369c9fbc4d1093905d92064e677e","parentId":"fld_af1cfccd393940bab36bf00dc91b4a84","modified":1660598122912,"created":1655917281699,"url":"{{ _.base_production }}/api/app/list/tenant","name":"List Companies","description":"Listagem de todas as empresas que estarão cadastradas no sistema da GoQuadra","method":"GET","body":{},"parameters":[],"headers":[],"authentication":{"type":"bearer","token":"{{ _.token }}"},"metaSortKey":-1655917281699,"isPrivate":false,"settingStoreCookies":true,"settingSendCookies":true,"settingDisableRenderRequestBody":false,"settingEncodeUrl":true,"settingRebuildPath":true,"settingFollowRedirects":"global","_type":"request"},{"_id":"req_f4cd035e141142768c6415630962b058","parentId":"fld_af1cfccd393940bab36bf00dc91b4a84","modified":1657805113870,"created":1655917281702,"url":"{{ _.base_production }}/api/app/user","name":"Read User","description":"Roda para o aplicativo utilizar, nessa rota o aplicativo irá listar todas as informações do usuário logado","method":"GET","body":{},"parameters":[],"headers":[],"authentication":{"type":"bearer","token":"{{ _.token }}"},"metaSortKey":-1655917281702,"isPrivate":false,"settingStoreCookies":true,"settingSendCookies":false,"settingDisableRenderRequestBody":true,"settingEncodeUrl":true,"settingRebuildPath":true,"settingFollowRedirects":"global","_type":"request"},{"_id":"req_dd925dea0d284e4d941ba70d8e162a96","parentId":"fld_af1cfccd393940bab36bf00dc91b4a84","modified":1660665178092,"created":1657045212740,"url":"{{ _.base_production }}/api/app/payments","name":"List Payments","description":"Listagem de todas as formas de pagamentos que estão cadastradas no sistema. Utilizada apenas no APP","method":"GET","body":{},"parameters":[],"headers":[],"authentication":{"type":"bearer","token":"{{ _.token }}"},"metaSortKey":-1655917281694,"isPrivate":false,"settingStoreCookies":true,"settingSendCookies":true,"settingDisableRenderRequestBody":false,"settingEncodeUrl":true,"settingRebuildPath":true,"settingFollowRedirects":"global","_type":"request"},{"_id":"env_72000a6a0a0cac97b034366f5a575a224fdea683","parentId":"wrk_b62daaa037c247f4adff53e54ef03eeb","modified":1660598110022,"created":1655817037793,"name":"Base Environment","data":{"base_url":"http://localhost:8000","base_production":"https://api.goquadra.com.br","token":"eyJ0eXAiOiJKV1QiLCJhbGciOiJIUzI1NiJ9.eyJpc3MiOiJodHRwczpcL1wvYXBpLmdvcXVhZHJhLmNvbS5iclwvYXBpXC9hdXRoXC9sb2dpbiIsImlhdCI6MTY2MDU5ODEwMSwiZXhwIjoxNjYxODA3NzAxLCJuYmYiOjE2NjA1OTgxMDEsImp0aSI6IjR0eTE2blVsemJzRVk5dW4iLCJzdWIiOjEsInBydiI6IjIzYmQ1Yzg5NDlmNjAwYWRiMzllNzAxYzQwMDg3MmRiN2E1OTc2ZjcifQ.GlRWjJ97_DnPouj_zC3U8wiHuoRVTaTv0whY0_1DaoY"},"dataPropertyOrder":{"&":["base_url","base_production","token"]},"color":null,"isPrivate":false,"metaSortKey":1655817037793,"_type":"environment"},{"_id":"jar_72000a6a0a0cac97b034366f5a575a224fdea683","parentId":"wrk_b62daaa037c247f4adff53e54ef03eeb","modified":1655817037798,"created":1655817037798,"name":"Default Jar","cookies":[],"_type":"cookie_jar"},{"_id":"spc_c1e58db0a78e4a549f0fda3daabbe6c5","parentId":"wrk_b62daaa037c247f4adff53e54ef03eeb","modified":1655925246813,"created":1655817037785,"fileName":"GoQuadra","contents":"","contentType":"yaml","_type":"api_spec"},{"_id":"uts_0ad0d96416b6411f8a41165e85a2695c","parentId":"wrk_b62daaa037c247f4adff53e54ef03eeb","modified":1655817037805,"created":1655817037805,"name":"Example Test Suite","_type":"unit_test_suite"}]}